vermin/__init__.py
vermin/arguments.py
vermin/backports.py
vermin/config.py
vermin/constants.py
vermin/detection.py
vermin/features.py
vermin/main.py
vermin/parser.py
vermin/printing.py
vermin/processor.py
vermin/rules.py
vermin/source_state.py
vermin/source_visitor.py
vermin/utility.py
vermin/formats/__init__.py
vermin/formats/default_format.py
vermin/formats/format.py
vermin/formats/github_format.py
vermin/formats/parsable_format.py
vermin-1.7.0.dist-info/licenses/LICENSE.txt
vermin-1.7.0.dist-info/METADATA
vermin-1.7.0.dist-info/WHEEL
vermin-1.7.0.dist-info/entry_points.txt
vermin-1.7.0.dist-info/top_level.txt
vermin-1.7.0.dist-info/RECORD
