Metadata-Version: 2.4
Name: vermin
Version: 1.7.0
Summary: Concurrently detect the minimum Python versions needed to run code
Home-page: https://github.com/netromdk/vermin
Author: Morten Kristensen
Author-email: me@mortens.dev
License: MIT
Project-URL: Bug Reports, https://github.com/netromdk/vermin/issues
Project-URL: Source, https://github.com/netromdk/vermin/
Keywords: version detection analysis ast development
Classifier: Development Status :: 5 - Production/Stable
Classifier: Intended Audience :: Developers
Classifier: Programming Language :: Python
Classifier: Programming Language :: Python :: 3.0
Classifier: License :: OSI Approved :: MIT License
Classifier: Topic :: Utilities
Classifier: Topic :: Software Development
Requires-Python: >=3.0
License-File: LICENSE.txt
Dynamic: author
Dynamic: author-email
Dynamic: classifier
Dynamic: description
Dynamic: home-page
Dynamic: keywords
Dynamic: license
Dynamic: license-file
Dynamic: project-url
Dynamic: requires-python
Dynamic: summary
